README.rst
setup.py
pennies/__init__.py
pennies/time.py
pennies.egg-info/PKG-INFO
pennies.egg-info/SOURCES.txt
pennies.egg-info/dependency_links.txt
pennies.egg-info/requires.txt
pennies.egg-info/top_level.txt
pennies/calculators/__init__.py
pennies/calculators/assets.py
pennies/calculators/payments.py
pennies/calculators/swaps.py
pennies/calculators/trades.py
pennies/market/__init__.py
pennies/market/curve_calibration.py
pennies/market/curves.py
pennies/market/interpolate.py
pennies/market/market.py
pennies/models/__init__.py
pennies/models/black.py
pennies/reporting/__init__.py
pennies/trading/__init__.py
pennies/trading/assets.py
pennies/trading/trades.py