Metadata-Version: 1.2
Name: pennies
Version: 0.2.0
Summary: pennies: pythonic quantitative finance library
Home-page: https://github.com/caseyclements/pennies
Maintainer: Casey Clements
Maintainer-email: casey.clements@gmail.com
License: BSD
Platform: Mac OS-X
Classifier: Development Status :: 1 - Planning
Classifier: Intended Audience :: Financial and Insurance Industry
Classifier: Intended Audience :: Developers
Classifier: License :: OSI Approved
Classifier: Programming Language :: Python
Classifier: Topic :: Software Development
Classifier: Topic :: Office/Business :: Financial
Classifier: Topic :: Scientific/Engineering
Classifier: Operating System :: Microsoft :: Windows
Classifier: Operating System :: POSIX
Classifier: Operating System :: Unix
Classifier: Operating System :: MacOS
